simdlib_module.cpython-313-darwin.so
simdlib/__init__.py
simdlib/simdlibmodule.c
tests/benchmark.py
tests/stock_example.py
tests/test_core.py
simdlib-0.1.1.dist-info/METADATA
simdlib-0.1.1.dist-info/WHEEL
simdlib-0.1.1.dist-info/top_level.txt
simdlib-0.1.1.dist-info/RECORD
