Metadata-Version: 2.4
Name: simdlib
Version: 0.1.1
Summary: SIMD-accelerated library for list computations
Author-email: Michael Zheng <qx2zheng@uwaterloo.ca>
License: MIT
Requires-Python: >=3.7
